aurigma/asset_storage/__init__.py
aurigma/asset_storage/api_client.py
aurigma/asset_storage/api_response.py
aurigma/asset_storage/configuration.py
aurigma/asset_storage/exceptions.py
aurigma/asset_storage/rest.py
aurigma/asset_storage/api/__init__.py
aurigma/asset_storage/api/artifacts_api.py
aurigma/asset_storage/api/build_info_api.py
aurigma/asset_storage/api/color_profiles_api.py
aurigma/asset_storage/api/data_schemas_api.py
aurigma/asset_storage/api/data_sets_api.py
aurigma/asset_storage/api/designs_api.py
aurigma/asset_storage/api/documents_api.py
aurigma/asset_storage/api/fonts_api.py
aurigma/asset_storage/api/images_api.py
aurigma/asset_storage/api/mockups_api.py
aurigma/asset_storage/api/palettes_api.py
aurigma/asset_storage/api/previews_api.py
aurigma/asset_storage/api/private_designs_api.py
aurigma/asset_storage/api/private_images_api.py
aurigma/asset_storage/api/private_mockups_api.py
aurigma/asset_storage/api/private_resources_api.py
aurigma/asset_storage/api/resources_api.py
aurigma/asset_storage/api/tenants_api.py
aurigma/asset_storage/models/__init__.py
aurigma/asset_storage/models/artifact_dto.py
aurigma/asset_storage/models/artifact_type.py
aurigma/asset_storage/models/asset_relation.py
aurigma/asset_storage/models/batch_conflict_dto.py
aurigma/asset_storage/models/batch_copy_input.py
aurigma/asset_storage/models/batch_copy_resources_input.py
aurigma/asset_storage/models/batch_delete_input.py
aurigma/asset_storage/models/batch_delete_resources_input.py
aurigma/asset_storage/models/batch_update_custom_fields_input.py
aurigma/asset_storage/models/batch_update_owner_input.py
aurigma/asset_storage/models/batch_update_parent_folder_input.py
aurigma/asset_storage/models/batch_update_resources_owner_input.py
aurigma/asset_storage/models/build_info_model.py
aurigma/asset_storage/models/color_profile_class.py
aurigma/asset_storage/models/color_profile_dto.py
aurigma/asset_storage/models/color_profile_metadata.py
aurigma/asset_storage/models/color_space.py
aurigma_asset_storage_api_client-1.0.0.dist-info/METADATA
aurigma_asset_storage_api_client-1.0.0.dist-info/WHEEL
aurigma_asset_storage_api_client-1.0.0.dist-info/top_level.txt
aurigma_asset_storage_api_client-1.0.0.dist-info/RECORD
